realtime_smm/__init__.py
realtime_smm/grid.py
realtime_smm/helpers/__init__.py
realtime_smm/helpers/nn.py
realtime_smm/helpers/robot.py
realtime_smm/helpers/store.py
realtime_smm/helpers/types.py
realtime_smm/learning.py
realtime_smm/main.py
realtime_smm/postprocess_grid.py
realtime_smm/smm_grid.py
realtime_smm-0.1.2.dist-info/METADATA
realtime_smm-0.1.2.dist-info/WHEEL
realtime_smm-0.1.2.dist-info/licenses/LICENSE
realtime_smm-0.1.2.dist-info/RECORD
