Metadata-Version: 2.4
Name: realtime-smm
Version: 0.1.2
Summary: 
License-File: LICENSE
Author: Landon Clark
Author-email: landonclark97@gmail.com
Requires-Python: >=3.11,<3.15
Classifier: Programming Language :: Python :: 3
Classifier: Programming Language :: Python :: 3.11
Classifier: Programming Language :: Python :: 3.12
Classifier: Programming Language :: Python :: 3.13
Classifier: Programming Language :: Python :: 3.14
Requires-Dist: networkx (>=3.5,<4.0)
Requires-Dist: numpy (>=2.3.3,<3.0.0)
Requires-Dist: platformdirs (>=4.4.0,<5.0.0)
Requires-Dist: scipy (>=1.16.2,<2.0.0)
Requires-Dist: tdqm (>=0.0.1,<0.0.2)
Requires-Dist: torch (>=2.9.0,<3.0.0)
Requires-Dist: zarr (>=3.1.3,<4.0.0)
